Workbook

Sheet Assumptions
C3: Input | D3: Output | E3: Notes
C4: Cost of Equity (r) | D4: 0.12 | E4: Discount rate used for FCFE Valuation
C5: Terminal Growth (g) | D5: 0.05 | E5: Longterm perptual Growth Assumption
C6: Shares Outstanding (crore) | D6: 415.09 | E6: Total Equity share of Infosys
C7: Start Year | D7: 2025 | E7: First FCFE Projection
C8: End Year | D8: 2029 | E8: Last Explicit Forecast Year
C10: Discount Rate- Low | D10: 0.12
C11: Discount Rate- Base | D11: 0.13
C12: Discount Rate - High | D12: 0.14
C14: Terminal Growth-Low | D14: 0.04
C15: Terminal Growth-Base | D15: 0.05
C16: Terminal Growth-High | D16: 0.06

Sheet FCFE_Forecast
D2: Year | E2: FCFE (₹ Crore) | F2: Discount Factor | G2: PV of FCFE (₹ Crore)
D3: 2025 | E3: 30571.4 | F3: =1/(1+Assumptions!$D$4)^(D3-Assumptions!$D$7+1) -> 0.89285714 | G3: =E3*F3 -> 27295.893
D4: =D3+1 -> 2026 | E4: 33628.54 | F4: =1/(1+Assumptions!$D$4)^(D4-Assumptions!$D$7+1) -> 0.79719388 | G4: =E4*F4 -> 26808.466
D5: =D4+1 -> 2027 | E5: 36991.39 | F5: =1/(1+Assumptions!$D$4)^(D5-Assumptions!$D$7+1) -> 0.71178025 | G5: =E5*F5 -> 26329.741
D6: =D5+1 -> 2028 | E6: 40690.53 | F6: =1/(1+Assumptions!$D$4)^(D6-Assumptions!$D$7+1) -> 0.63551808 | G6: =E6*F6 -> 25859.567
D7: =D6+1 -> 2029 | E7: 44759.58 | F7: =1/(1+Assumptions!$D$4)^(D7-Assumptions!$D$7+1) -> 0.56742686 | G7: =E7*F7 -> 25397.788
D9: Terminal Value (end of 2029) | E9: =E7*(1+Assumptions!D5)/(Assumptions!D4-Assumptions!D5) -> 671393.7
D10: PV of Terminal Value | E10: =E9*F7 -> 380966.82

Sheet Valuation Summary
B2: PV of FCFE (2025 - 2029) | C2: =SUM(FCFE_Forecast!G3:G7) -> 131691.45 | F2: Sensitivity- Intrinsic Value per share
B3: PV of Terminal Value | C3: =FCFE_Forecast!E10 -> 380966.82
B4: Total Equity Value (₹ Crore) | C4: =C2+C3 -> 512658.27 | E4: g/r | F4: =$C$5 -> 1235.0533 | G4: 0.12 | H4: 0.13 | I4: 0.14
B5: Intrinsic Value per Share (₹) | C5: =C4/Assumptions!D6 -> 1235.0533 | F5: 0.04 | G5: =( SUM(FCFE_Forecast!$G$3:$G$7) + (FCFE_Forecast!$E$7*(1+$F5)/(G$4-$F5))*FCFE_Forecast!$F$7 )/Assumptions!$D$6 -> 1112.6809 | H5: =( SUM(FCFE_Forecast!$G$3:$G$7) + (FCFE_Forecast!$E$7*(1+$F5)/(H$4-$F5))*FCFE_Forecast!$F$7 )/Assumptions!$D$6 -> 1024.3008 | I5: =( SUM(FCFE_Forecast!$G$3:$G$7) + (FCFE_Forecast!$E$7*(1+$F5)/(I$4-$F5))*FCFE_Forecast!$F$7 )/Assumptions!$D$6 -> 953.59668
F6: 0.05 | G6: =( SUM(FCFE_Forecast!$G$3:$G$7) + (FCFE_Forecast!$E$7*(1+$F6)/(G$4-$F6))*FCFE_Forecast!$F$7 )/Assumptions!$D$6 -> 1235.0533 | H6: =( SUM(FCFE_Forecast!$G$3:$G$7) + (FCFE_Forecast!$E$7*(1+$F6)/(H$4-$F6))*FCFE_Forecast!$F$7 )/Assumptions!$D$6 -> 1120.3291 | I6: =( SUM(FCFE_Forecast!$G$3:$G$7) + (FCFE_Forecast!$E$7*(1+$F6)/(I$4-$F6))*FCFE_Forecast!$F$7 )/Assumptions!$D$6 -> 1031.0992
F7: 0.06 | G7: =( SUM(FCFE_Forecast!$G$3:$G$7) + (FCFE_Forecast!$E$7*(1+$F7)/(G$4-$F7))*FCFE_Forecast!$F$7 )/Assumptions!$D$6 -> 1398.2165 | H7: =( SUM(FCFE_Forecast!$G$3:$G$7) + (FCFE_Forecast!$E$7*(1+$F7)/(H$4-$F7))*FCFE_Forecast!$F$7 )/Assumptions!$D$6 -> 1243.7942 | I7: =( SUM(FCFE_Forecast!$G$3:$G$7) + (FCFE_Forecast!$E$7*(1+$F7)/(I$4-$F7))*FCFE_Forecast!$F$7 )/Assumptions!$D$6 -> 1127.9774
